<?xml version = '1.0' encoding = 'UTF-8'?>
<FKIndexAssociation class="oracle.dbtools.crest.model.design.relational.FKIndexAssociation" directorySegmentName="seg_0" id="6FB1FC5C-779F-7E4E-B068-4891C8FF32D2" containerWithKeyObject="4BB016CE-5AC8-BAB4-0803-DAC8858E5FDD" localFKIndex="C4388E48-FD48-C23A-635C-14619431D878" name="TABLE_12_Proizvod_FK">
<createdBy>Ana Mandic</createdBy>
<createdTime>2024-10-15 15:38:46 UTC</createdTime>
<ownerDesignName>Temu</ownerDesignName>
<referredTableLongName>Proizvod</referredTableLongName>
<deleteRule>NO ACTION</deleteRule>
<referredTableID>E8CF5A21-3091-A0FC-60AD-96ADC90404D9</referredTableID>
<keyObject>6B5A74BF-F53D-496B-C24B-03368BDFBC35</keyObject>
<referredKeyID>6B5A74BF-F53D-496B-C24B-03368BDFBC35</referredKeyID>
<mandatory>true</mandatory>
<refColNames>id_proizvoda</refColNames>
<transferable>true</transferable>
<rely>false</rely>
<columnDependencyConstraintGenerateInDDL>true</columnDependencyConstraintGenerateInDDL>
</FKIndexAssociation>
